elf_size_analyze/__init__.py
elf_size_analyze/__main__.py
elf_size_analyze/argument_parser.py
elf_size_analyze/color.py
elf_size_analyze/misc.py
elf_size_analyze/plotly.py
elf_size_analyze/section.py
elf_size_analyze/symbol.py
elf_size_analyze/symbol_tree.py
elf_size_analyze/tree.py
elf_size_analyze/html/gen.py
elf_size_analyze/html/index.js
elf_size_analyze/html/styles.css
elf_size_analyze-0.3.1.dist-info/licenses/LICENSE
elf_size_analyze-0.3.1.dist-info/METADATA
elf_size_analyze-0.3.1.dist-info/WHEEL
elf_size_analyze-0.3.1.dist-info/entry_points.txt
elf_size_analyze-0.3.1.dist-info/top_level.txt
elf_size_analyze-0.3.1.dist-info/RECORD
