Metadata-Version: 2.4
Name: elf-size-analyze
Version: 0.3.1
Summary: Tool to extract information about symbols and sections from an ELF file and filters them.
Author: Jedrzej Boczar, Dominic Kuschmierz, Adel Mamin, Amir Gonnen
License-Expression: Apache-2.0
Project-URL: Homepage, https://github.com/jedrzejboczar/elf-size-analyze
Project-URL: Bug Tracker, https://github.com/jedrzejboczar/elf-size-analyze/issues
Classifier: Programming Language :: Python :: 3
Classifier: Operating System :: OS Independent
Classifier: Topic :: Software Development :: Compilers
Classifier: Topic :: Software Development :: Debuggers
Requires-Python: >=3.7
License-File: LICENSE
Provides-Extra: dev
Requires-Dist: pylint==2.6.0; extra == "dev"
Requires-Dist: pytest==7.2.0; extra == "dev"
Requires-Dist: black==20.8b1; extra == "dev"
Provides-Extra: plotly
Requires-Dist: plotly==6.3.0; extra == "plotly"
Requires-Dist: pandas==2.3.3; extra == "plotly"
Requires-Dist: numpy==2.3.3; extra == "plotly"
Dynamic: license-file
